{
  "name": "your-project-name",
  "sources": [
    {
      "dir": "src",
      "subdirs": true
    },
    {
      "dir": "app",
      "subdirs": true
    },
    {
      "dir": "components",
      "subdirs": true
    },
    {
      "dir": "tests",
      "subdirs": true,
      "type": "dev"
    }
  ],
  "jsx": { "version": 4 },
  "package-specs": [
    {
      "module": "esmodule",
      "in-source": true
    }
  ],
  "suffix": ".res.mjs",
  "bs-dependencies": [
    "@rescript/core",
    "@rescript/react",
    "rescript-react-native",
    "rescript-vitest"
  ],
  "bsc-flags": [
    "-open RescriptCore"
  ],
  "gentypeconfig": {
    "module": "esmodule",
    "moduleResolution": "node",
    "generatedFileExtension": ".gen.tsx",
    "debug": { "all": false, "basic": false }
  }
}

